odoo/addons/aresta/__init__.py
odoo/addons/aresta/__manifest__.py
odoo/addons/aresta/i18n/ca_ES.po
odoo/addons/aresta/i18n/es.po
odoo/addons/aresta/models/__init__.py
odoo/addons/aresta/models/sale_order.py
odoo/addons/aresta/report/__init__.py
odoo/addons/aresta/report/delivery_note_mail_template.xml
odoo/addons/aresta/report/sale_report.py
odoo/addons/aresta/report/stock_report_deliveryslip.xml
odoo/addons/aresta/report/stock_report_views.xml
odoo/addons/aresta/views/sale_order.xml
odoo/addons/aresta/views/sale_report.xml
odoo/addons/aresta/wizards/__init__.py
odoo/addons/aresta/wizards/confirm_sale_order/__init__.py
odoo/addons/aresta/wizards/confirm_sale_order/confirm_sale_order.py
odoo/addons/aresta/wizards/confirm_sale_order/confirm_sale_order.xml
odoo/addons/aresta/wizards/send_delivery_note/__init__.py
odoo/addons/aresta/wizards/send_delivery_note/send_delivery_note.py
odoo/addons/aresta/wizards/send_delivery_note/send_delivery_note.xml
odoo14_addon_aresta-14.0.1.0.3.dist-info/METADATA
odoo14_addon_aresta-14.0.1.0.3.dist-info/WHEEL
odoo14_addon_aresta-14.0.1.0.3.dist-info/top_level.txt
odoo14_addon_aresta-14.0.1.0.3.dist-info/RECORD
